jupyterlab_henanigans/__init__.py
jupyterlab_henanigans/labextension/package.json
jupyterlab_henanigans/labextension/static/181.cde75d2542b249b51729.js
jupyterlab_henanigans/labextension/static/509.f6a00a1f79c4dfe71d5e.js
jupyterlab_henanigans/labextension/static/remoteEntry.400bc951e95362e41c92.js
jupyterlab_henanigans/labextension/static/style.js
jupyterlab_henanigans/labextension/static/third-party-licenses.json
jupyterlab_henanigans/labextension/themes/jupyterlab_henanigans/index.css
jupyterlab_henanigans/labextension/themes/jupyterlab_henanigans/index.js
jupyterlab_henanigans-0.4.2.data/data/share/jupyter/labextensions/jupyterlab_henanigans/package.json
jupyterlab_henanigans-0.4.2.data/data/share/jupyter/labextensions/jupyterlab_henanigans/static/181.cde75d2542b249b51729.js
jupyterlab_henanigans-0.4.2.data/data/share/jupyter/labextensions/jupyterlab_henanigans/static/509.f6a00a1f79c4dfe71d5e.js
jupyterlab_henanigans-0.4.2.data/data/share/jupyter/labextensions/jupyterlab_henanigans/static/remoteEntry.400bc951e95362e41c92.js
jupyterlab_henanigans-0.4.2.data/data/share/jupyter/labextensions/jupyterlab_henanigans/static/style.js
jupyterlab_henanigans-0.4.2.data/data/share/jupyter/labextensions/jupyterlab_henanigans/static/third-party-licenses.json
jupyterlab_henanigans-0.4.2.data/data/share/jupyter/labextensions/jupyterlab_henanigans/themes/jupyterlab_henanigans/index.css
jupyterlab_henanigans-0.4.2.data/data/share/jupyter/labextensions/jupyterlab_henanigans/themes/jupyterlab_henanigans/index.js
jupyterlab_henanigans-0.4.2.data/data/share/jupyter/labextensions/jupyterlab_henanigans/install.json
jupyterlab_henanigans-0.4.2.dist-info/METADATA
jupyterlab_henanigans-0.4.2.dist-info/WHEEL
jupyterlab_henanigans-0.4.2.dist-info/licenses/LICENSE
jupyterlab_henanigans-0.4.2.dist-info/RECORD
