Metadata-Version: 2.4
Name: jupyterlab_henanigans
Version: 0.4.2
Summary: Henanigans theme for Jupyter Lab.
Project-URL: repository, https://github.com/theNewFlesh/jupyterlab_henanigans
Project-URL: documentation, https://theNewFlesh.github.io/jupyterlab_henanigans
Author-email: Alex Braun <alexander.g.braun@gmail.com>
License-Expression: MIT
License-File: LICENSE
Keywords: jupyter,jupyter-lab,theme
Classifier: Development Status :: 4 - Beta
Classifier: Intended Audience :: Developers
Classifier: License :: OSI Approved :: MIT License
Classifier: Programming Language :: Python :: 3
Classifier: Programming Language :: Python :: 3.10
Classifier: Programming Language :: Python :: 3.11
Classifier: Programming Language :: Python :: 3.12
Classifier: Programming Language :: Python :: 3.13
Classifier: Typing :: Typed
Requires-Python: >=3.10
